eeg_analysis/__init__.py
eeg_analysis/data_processing.py
eeg_analysis/main.py
eeg_analysis/plotting.py
eeg_analysis/data/after.csv
eeg_analysis/data/before.csv
eeg_analysis/data/during.csv
eeg_analysis/data/id_iskcon_data.csv
eeg_analysis-0.1.3.dist-info/LICENSE.txt
eeg_analysis-0.1.3.dist-info/METADATA
eeg_analysis-0.1.3.dist-info/WHEEL
eeg_analysis-0.1.3.dist-info/entry_points.txt
eeg_analysis-0.1.3.dist-info/top_level.txt
eeg_analysis-0.1.3.dist-info/RECORD
