Metadata-Version: 2.1
Name: eeg-analysis
Version: 0.1.3
Summary: A library for processing and plotting EEG data
Home-page: https://github.com/KarthikDani/PHCCOProject/tree/main/gsmm
Author: Karthik Dani
Author-email: karthikdani14@gmail.com
License: MIT
Classifier: Development Status :: 3 - Alpha
Classifier: Programming Language :: Python :: 3
Classifier: License :: OSI Approved :: MIT License
Classifier: Operating System :: OS Independent
Classifier: Intended Audience :: Science/Research
Classifier: Topic :: Scientific/Engineering :: Information Analysis
Requires-Python: >=3.7
License-File: LICENSE.txt
Requires-Dist: pandas
Requires-Dist: seaborn
Requires-Dist: matplotlib
Requires-Dist: scipy
